[
    {
        "content": "<p><span class=\"user-mention\" data-user-id=\"256729\">@klonos</span> Have you every had a drupal relatedcookie related problem with CloudFlare?</p>",
        "id": 207591271,
        "sender_full_name": "larsdesigns",
        "timestamp": 1597970941
    },
    {
        "content": "<p>Nope. I haven't used CloudFlare before <span aria-label=\"shrug\" class=\"emoji emoji-1f937\" role=\"img\" title=\"shrug\">:shrug:</span></p>",
        "id": 207591292,
        "sender_full_name": "klonos",
        "timestamp": 1597970984
    }
]