[
    {
        "content": "<p>I don't see a <code>html_tag</code> element on the form API page. Does it exist in Backdrop?</p>",
        "id": 217777406,
        "sender_full_name": "Laryn",
        "timestamp": 1606235076
    },
    {
        "content": "<p><a href=\"https://api.backdropcms.org/form_api#Elements\">https://api.backdropcms.org/form_api#Elements</a></p>",
        "id": 217777467,
        "sender_full_name": "Laryn",
        "timestamp": 1606235102
    },
    {
        "content": "<p>Trying to figure out if this issue is to add the functionality or change existing functionality: <br>\n<a href=\"https://github.com/backdrop/backdrop-issues/issues/3892\">https://github.com/backdrop/backdrop-issues/issues/3892</a></p>\n<div class=\"message_embed\"><a class=\"message_embed_image\" href=\"https://github.com/backdrop/backdrop-issues/issues/3892\" style=\"background-image: url(https://avatars3.githubusercontent.com/u/5283039?s=400&amp;v=4)\"></a><div class=\"data-container\"><div class=\"message_embed_title\"><a href=\"https://github.com/backdrop/backdrop-issues/issues/3892\" title=\"[D8][DX] Backport D8 `html_tag` element changes 路 Issue #3892 路 backdrop/backdrop-issues\">[D8][DX] Backport D8 `html_tag` element changes 路 Issue #3892 路 backdrop/backdrop-issues</a></div><div class=\"message_embed_description\">This is the respective issue for https://www.drupal.org/project/drupal/issues/2981726 in the D7 core queue: One year ago, the Drupal 8 html_tag has been updated and it&#39;s now able to render nest...</div></div></div>",
        "id": 217777697,
        "sender_full_name": "Laryn",
        "timestamp": 1606235202
    }
]