[
    {
        "content": "<p>FYI: <a href=\"https://forum.backdropcms.org/forum/issue-metatag-module\">https://forum.backdropcms.org/forum/issue-metatag-module</a></p>",
        "id": 213986134,
        "sender_full_name": "StPaulTim",
        "timestamp": 1603231928
    },
    {
        "content": "<p>There's some progress in the Metatag issue queue, two new pull requests are ready for testing.</p>\n<p><a href=\"https://github.com/backdrop-contrib/metatag/pulls\">https://github.com/backdrop-contrib/metatag/pulls</a></p>\n<p>Feel free to set appropriate labels for the two new issues - I don't have permission to do that.</p>\n<div class=\"message_embed\"><a class=\"message_embed_image\" href=\"https://github.com/backdrop-contrib/metatag/pulls\" style=\"background-image: url(https://avatars1.githubusercontent.com/u/7720679?s=400&amp;v=4)\"></a><div class=\"data-container\"><div class=\"message_embed_title\"><a href=\"https://github.com/backdrop-contrib/metatag/pulls\" title=\"backdrop-contrib/metatag\">backdrop-contrib/metatag</a></div><div class=\"message_embed_description\">Add structured metadata, aka \"meta tags\", for various pages on your site. - backdrop-contrib/metatag</div></div></div>",
        "id": 214072458,
        "sender_full_name": "indigoxela",
        "timestamp": 1603296137
    }
]